[{"name":"/welcome","nodes":[{"id":"1331061d-0965-e37f-1d4b-644bdccd86e2","type":"Page","parameters":{"styleCss":"background-color: white;"},"ports":[],"children":[{"id":"8ed3483a-ce78-a45c-3488-0f1c7f2d8a9b","type":"Group","parameters":{"justifyContent":"flex-start","sizeMode":"explicit","flexDirection":"column","position":"relative","height":{"value":90,"unit":"vh"}},"ports":[],"children":[{"id":"5efdce39-8d5b-e59d-5e61-9bee0c97ce7b","type":"Image","parameters":{"src":"Background.png","sizeMode":"explicit","width":{"value":100,"unit":"%","isFixed":false},"objectFit":"fill","height":{"value":100,"unit":"%","isFixed":false}},"ports":[],"children":[]},{"id":"8eb500df-8531-7442-8a6d-06467adffe89","type":"Image","parameters":{"src":"Accent 2.png","position":"absolute","marginLeft":{"value":16,"unit":"px"},"marginTop":{"value":16,"unit":"px"}},"ports":[],"children":[]},{"id":"fe6efb91-c5e3-a17c-cd12-83f424ebcc18","type":"Image","parameters":{"src":"Accent.png","position":"absolute","alignY":"bottom","alignX":"right","marginBottom":{"value":160,"unit":"px"},"marginRight":{"value":16,"unit":"px"}},"ports":[],"children":[]},{"id":"1aac8cef-97dd-5375-6752-c2f1e41ecceb","type":"Group","parameters":{"position":"absolute","alignItems":"center","justifyContent":"flex-start","alignY":"top","marginTop":{"value":0,"unit":"%"},"sizeMode":"explicit","paddingTop":{"value":48,"unit":"px"},"paddingBottom":{"value":48,"unit":"px"}},"ports":[],"children":[{"id":"b87f803c-b15e-035c-5aa1-3cda955fcf2e","type":"Image","parameters":{"src":"logo.png","position":"relative","sizeMode":"contentHeight","width":{"value":60,"unit":"%"},"minWidth":{"value":320,"unit":"px"},"zIndex":100},"ports":[],"children":[]},{"id":"43e87297-dd0f-f7b1-a51a-c30294432a66","type":"Text","parameters":{"text":"Empowering the future generation","textAlignX":"center","textAlignY":"center","position":"relative","color":"Primary Light","alignY":"top","sizeMode":"contentHeight"},"ports":[],"children":[]},{"id":"855c69d1-dc83-cb46-1d30-2e6de6c91cdd","type":"Group","parameters":{"sizeMode":"contentHeight","width":{"value":60,"unit":"%"},"backgroundColor":"#F4F5FF","borderRadius":{"value":10,"unit":"px"},"paddingTop":{"value":24,"unit":"px"},"paddingBottom":{"value":24,"unit":"px"},"maxWidth":{"value":480,"unit":"px"},"alignY":"top","position":"relative","alignX":"center","zIndex":100},"ports":[],"children":[{"id":"49b0afa5-07ca-af9a-69b6-12d4cda91150","type":"net.noodl.controls.textinput","parameters":{"label":"Take a tour of the platform","sizeMode":"explicit","marginBottom":{"value":12,"unit":"px"},"width":{"value":80,"unit":"%"},"alignX":"center","placeholder":"Enter your name"},"ports":[],"children":[]},{"id":"b003ef72-e9c1-3d5a-fdcd-c26ec76f393c","type":"/Reusable/Demo Navigator","parameters":{"User":"Explore as a student"},"ports":[],"children":[]}]}]}]},{"id":"6ed475af-4dc1-9c81-3c8c-106323ce22d3","type":"Group","parameters":{"sizeMode":"contentHeight","height":{"value":120,"unit":"px"},"width":{"value":80,"unit":"%"},"alignX":"center"},"ports":[],"children":[{"id":"c946306a-1bd4-9ae4-9400-cb841566ea77","type":"Text","parameters":{"text":"A platform to connect","textAlignX":"center","alignY":"center","textAlignY":"center","marginBottom":{"value":16,"unit":"px"},"textStyle":"Title Large","marginTop":{"value":60,"unit":"px"}},"ports":[],"children":[]},{"id":"c47242d2-ef7f-7d4f-6407-428cdaa19a84","type":"net.noodl.controls.button","parameters":{"backgroundColor":"Accent","textStyle":"Title Large","color":"Primary Dark","label":"students, caregivers, and industries","alignX":"center","sizeMode":"contentSize","paddingTop":{"value":12,"unit":"px"},"marginBottom":{"value":40,"unit":"px"},"paddingBottom":{"value":12,"unit":"px"},"fontSize":{"value":24,"unit":"px"}},"ports":[],"children":[]},{"id":"62290390-97c1-4358-24b4-afec530277c8","type":"Image","parameters":{"src":"Diagram.png","position":"relative","alignY":"bottom","alignX":"center","marginBottom":{"value":64,"unit":"px"},"marginRight":{"value":16,"unit":"px"},"maxWidth":{"value":480,"unit":"px"},"marginLeft":{"value":16,"unit":"px"},"sizeMode":"contentHeight"},"ports":[],"children":[]}]},{"id":"3d625d3c-ff3b-8aa5-fcbb-3cdbb7bca3a9","type":"Group","parameters":{"backgroundColor":"Primary Subtle"},"ports":[],"children":[{"id":"20060682-89c1-7361-d1cc-29d03719a687","type":"Text","parameters":{"text":"Through EmpowerED you can","textAlignX":"center","alignY":"center","textAlignY":"center","marginBottom":{"value":16,"unit":"px"},"textStyle":"Title Large","marginTop":{"value":60,"unit":"px"},"marginLeft":{"value":0,"unit":"px"}},"ports":[],"children":[]},{"id":"dcd9802d-bb41-cc6f-2bf5-b2531f2f93c8","type":"Group","parameters":{"flexDirection":"row","alignX":"center","justifyContent":"center","paddingLeft":{"value":16,"unit":"px"},"paddingRight":{"value":16,"unit":"px"}},"ports":[],"children":[{"id":"f0a70530-d989-c25a-2c68-d88e2b891d0d","type":"/Reusable/Icon and text","parameters":{"Icon":"classmates.png","Caption":"Students"},"ports":[],"children":[]},{"id":"5049a167-90ff-4c4d-e75d-886ca43ed514","type":"Group","parameters":{"sizeMode":"contentHeight","width":{"value":100,"unit":"%"},"maxWidth":{"value":360,"unit":"px"}},"ports":[],"children":[{"id":"00650a16-c04b-8571-3ab8-a439beffbdf5","type":"Text","parameters":{"text":"• Connect with new opportunities"},"ports":[],"children":[]},{"id":"626b91c3-4448-3998-9672-ba69f00996bb","type":"Text","parameters":{"text":"• Translate experience into marketable skills"},"ports":[],"children":[]},{"id":"04bd7db5-4862-64d3-4f45-af73ec56cd57","type":"Text","parameters":{"text":"• Understand what skills employers are looking for"},"ports":[],"children":[]}]}]},{"id":"b9f857a8-ce90-15ab-63c4-91bbf65a4d5c","type":"Group","parameters":{"flexDirection":"row","justifyContent":"center","paddingLeft":{"value":16,"unit":"px"},"paddingRight":{"value":16,"unit":"px"}},"ports":[],"children":[{"id":"d8cd3b69-6808-163e-6761-c04bde306fda","type":"/Reusable/Icon and text","parameters":{"Icon":"parents.png","Caption":"Caregivers"},"ports":[],"children":[]},{"id":"98ee0afa-5f91-f223-5311-186f51bf3a8b","type":"Group","parameters":{"sizeMode":"contentHeight","width":{"value":100,"unit":"%"},"maxWidth":{"value":360,"unit":"px"}},"ports":[],"children":[{"id":"853db8d0-0d60-edba-0c69-e8762bf1bd1c","type":"Text","parameters":{"text":"• Connect with other caregivers"},"ports":[],"children":[]},{"id":"b9136edd-c245-0d20-f4df-425b2e9f45ac","type":"Text","parameters":{"text":"• Support your student"},"ports":[],"children":[]},{"id":"98f59016-931e-789f-f5bc-40af82ecd22e","type":"Text","parameters":{"text":"• Access curated podcasts and articles"},"ports":[],"children":[]}]}]},{"id":"6f4876b9-3ec5-84cb-d252-5af9a4973b2d","type":"Group","parameters":{"flexDirection":"row","justifyContent":"center","paddingLeft":{"value":16,"unit":"px"},"paddingRight":{"value":16,"unit":"px"}},"ports":[],"children":[{"id":"c4e91926-0f8c-c6e5-aff0-815d8e989a36","type":"/Reusable/Icon and text","parameters":{"Icon":"office-building.png","Caption":"Industry"},"ports":[],"children":[]},{"id":"8903aaff-b0ee-a9fa-5bac-3807aa5c8562","type":"Group","parameters":{"sizeMode":"contentHeight","width":{"value":100,"unit":"%"},"maxWidth":{"value":360,"unit":"px"}},"ports":[],"children":[{"id":"44a07bf4-071f-73c4-cc62-67f69436ac72","type":"Text","parameters":{"text":"• Connect with future workforce"},"ports":[],"children":[]},{"id":"7fc622c6-7462-1092-e0c3-308ce06fc7b3","type":"Text","parameters":{"text":"• Promote company values"},"ports":[],"children":[]},{"id":"2e898989-78d8-beb2-ee08-6b4d1b0a693c","type":"Text","parameters":{"text":"• Advertise recent innovation"},"ports":[],"children":[]}]}]}]},{"id":"0f9d762c-b4f2-a4c8-f02e-da749832872c","type":"Group","parameters":{"paddingBottom":{"value":80,"unit":"px"}},"ports":[],"children":[{"id":"7992752b-6f18-3a64-a91a-1a99a6e8b983","type":"Text","parameters":{"text":"What can we help you with?","textAlignX":"center","alignY":"center","textAlignY":"center","marginBottom":{"value":40,"unit":"px"},"textStyle":"Title Large","marginTop":{"value":120,"unit":"px"}},"ports":[],"children":[]},{"id":"a9200de7-353e-710d-f59e-e7586a7d8e8d","type":"Group","parameters":{"flexDirection":"row","marginBottom":{"value":60,"unit":"px"},"sizeMode":"contentHeight","alignX":"center","width":{"value":60,"unit":"%"}},"ports":[],"children":[{"id":"14d8e38c-a675-3d25-18df-2b9515a3638f","type":"net.noodl.controls.textinput","parameters":{"label":"","sizeMode":"explicit","width":{"value":60,"unit":"%"},"alignX":"center","marginLeft":{"value":24,"unit":"px"},"maxWidth":{"value":480,"unit":"px"},"placeholder":"Search for topics and resources using AI"},"ports":[],"children":[]},{"id":"cca28b9a-c8ab-8440-43d6-7e58af38530c","type":"net.noodl.visual.icon","parameters":{"iconIconSource":{"class":"material-icons","code":"search","codeAsClass":false},"iconColor":"Primary","iconSize":{"value":40,"unit":"px"},"alignY":"bottom","alignX":"left"},"ports":[],"children":[]}]}]},{"id":"96186558-9f93-93c5-52ab-286b45198ce9","type":"Group","parameters":{"backgroundColor":"Primary Dark","paddingTop":{"value":32,"unit":"px"},"paddingBottom":{"value":32,"unit":"px"},"paddingLeft":{"value":16,"unit":"px"},"marginRight":{"value":16,"unit":"px"},"sizeMode":"contentHeight"},"ports":[],"children":[{"id":"866fe86e-6d48-18dd-a9a4-b113b0c9527f","type":"net.noodl.visual.columns","parameters":{"layoutString":"2 1 1"},"ports":[],"children":[{"id":"f712c127-b369-83cf-3b25-b457c6fd18af","type":"Group","parameters":{},"ports":[],"children":[{"id":"759bfffc-0a32-99a8-6548-aa22c82e55cd","type":"Image","parameters":{"src":"logo.png","maxWidth":{"value":240,"unit":"px"},"sizeMode":"contentHeight"},"ports":[],"children":[]}]},{"id":"3f7669a4-8e15-ea98-22c2-6e9dd5eb9ec8","type":"Group","parameters":{},"ports":[],"children":[{"id":"c9d8e15a-387c-9da7-a5bd-f1e7074da4d0","type":"Text","variant":"Footer","parameters":{"text":"Home"},"stateParameters":{},"stateTransitions":{},"defaultStateTransitions":{},"ports":[],"children":[]},{"id":"38a4605f-e4f1-b180-7e2e-6c4d4ffcffd6","type":"Text","variant":"Footer","parameters":{"text":"Log in"},"stateParameters":{},"stateTransitions":{},"defaultStateTransitions":{},"ports":[],"children":[]},{"id":"85c353fc-064e-c49d-6814-a027a410e01e","type":"Text","variant":"Footer","parameters":{"text":"Sign up"},"stateParameters":{},"stateTransitions":{},"defaultStateTransitions":{},"ports":[],"children":[]},{"id":"f7c0489d-da10-efd4-49e5-9bd718a2d26a","type":"Text","variant":"Footer","parameters":{"text":"Resources\n"},"stateParameters":{},"stateTransitions":{},"defaultStateTransitions":{},"ports":[],"children":[]}]},{"id":"e87c7d6d-0a96-03db-7a24-ddb1f4a15927","type":"Group","parameters":{},"ports":[],"children":[{"id":"e05e9a89-4646-e6e2-608b-425325cbbc1d","type":"Text","variant":"Footer","parameters":{"text":"Virtual"},"stateParameters":{},"stateTransitions":{},"defaultStateTransitions":{},"ports":[],"children":[]},{"id":"fa6459ab-1694-48c9-9e17-9c33784f81a1","type":"Text","variant":"Footer","parameters":{"text":"About Us"},"stateParameters":{},"stateTransitions":{},"defaultStateTransitions":{},"ports":[],"children":[]},{"id":"8810f0e8-7270-6ce2-2e7d-9213dc1ccdf5","type":"Text","variant":"Footer","parameters":{"text":"Contact"},"stateParameters":{},"stateTransitions":{},"defaultStateTransitions":{},"ports":[],"children":[]},{"id":"ba611579-309b-0f01-82ee-c5864421d7d0","type":"Text","variant":"Footer","parameters":{"text":"FAQs"},"stateParameters":{},"stateTransitions":{},"defaultStateTransitions":{},"ports":[],"children":[]}]}]}]}]},{"id":"264e77ba-ba5b-a4b8-d40f-b0fe5349e433","type":"PageInputs","parameters":{},"ports":[],"children":[]},{"id":"b59fab04-6fe5-3ac7-525e-d31ac91cf3eb","type":"Set Variable","parameters":{"name":"MountHeader","setWith":"boolean","value":true},"ports":[],"children":[]},{"id":"d68c57e7-2898-d4bf-3004-e33b53466181","type":"PageStackNavigateToPath","parameters":{"path":"/student"},"ports":[],"children":[]},{"id":"5d2ea492-1476-f40b-30cc-2abbe522581e","type":"Set Variable","parameters":{"name":"Name","setWith":"string"},"ports":[],"children":[]},{"id":"b87dc9fa-5f86-b2b2-7453-bbb56e34c695","type":"Expression","parameters":{"expression":"username === \"\" || username === 0 ? \"Student\" : username"},"ports":[],"children":[]}],"connections":[{"sourceId":"b59fab04-6fe5-3ac7-525e-d31ac91cf3eb","sourcePort":"done","targetId":"d68c57e7-2898-d4bf-3004-e33b53466181","targetPort":"navigate"},{"sourceId":"5d2ea492-1476-f40b-30cc-2abbe522581e","sourcePort":"done","targetId":"b59fab04-6fe5-3ac7-525e-d31ac91cf3eb","targetPort":"do"},{"sourceId":"49b0afa5-07ca-af9a-69b6-12d4cda91150","sourcePort":"onTextChanged","targetId":"b87dc9fa-5f86-b2b2-7453-bbb56e34c695","targetPort":"username"},{"sourceId":"b87dc9fa-5f86-b2b2-7453-bbb56e34c695","sourcePort":"result","targetId":"5d2ea492-1476-f40b-30cc-2abbe522581e","targetPort":"value"},{"sourceId":"b003ef72-e9c1-3d5a-fdcd-c26ec76f393c","sourcePort":"Clicked","targetId":"5d2ea492-1476-f40b-30cc-2abbe522581e","targetPort":"do"}],"ports":[],"roots":["1331061d-0965-e37f-1d4b-644bdccd86e2"]}]